{
  "id": 9,
  "country": "Chile",
  "city": "CHEPICA",
  "name": "Alimentos Buencampo SPA",
  "contact": "ROSITA SALINAS",
  "whatsapp": "56990436406",
  "email": "rosita@buencampo.cl",
  "organic_certification": "CERTIFICADO",
  "bd_certification": "En transicion",
  "parcels": [
    {
      "product": "Acedera",
      "variety": null,
      "surface": 60,
      "surface_unit": "m2",
      "production": null,
      "production_unit": null,
      "market": "Local",
      "observations": null
    },
    {
      "product": "Acelga",
      "variety": "Crespa ,lisa y colores",
      "surface": 100,
      "surface_unit": "m2",
      "production": null,
      "production_unit": null,
      "market": "Local",
      "observations": null
    },
    {
      "product": "Ají",
      "variety": "Cristal, americano",
      "surface": 100,
      "surface_unit": "m2",
      "production": null,
      "production_unit": null,
      "market": "Local",
      "observations": null
    },
    {
      "product": "Pradera trébol/ballica",
      "variety": null,
      "surface": 800,
      "surface_unit": "m2",
      "production": null,
      "production_unit": null,
      "market": "Local",
      "observations": null
    },
    {
      "product": "Betarraga hojas",
      "variety": null,
      "surface": 50,
      "surface_unit": "m2",
      "production": null,
      "production_unit": null,
      "market": "Local",
      "observations": null
    },
    {
      "product": "Cilantro",
      "variety": "Santos",
      "surface": 240,
      "surface_unit": "m2",
      "production": null,
      "production_unit": null,
      "market": "Local",
      "observations": null
    },
    {
      "product": "Cibulette",
      "variety": null,
      "surface": 50,
      "surface_unit": "m2",
      "production": null,
      "production_unit": null,
      "market": "Local",
      "observations": null
    },
    {
      "product": "Frutillas",
      "variety": "Camara rosa,",
      "surface": 560,
      "surface_unit": "m2",
      "production": null,
      "production_unit": null,
      "market": "Local",
      "observations": null
    },
    {
      "product": "Floresde corte Aster",
      "variety": null,
      "surface": 50,
      "surface_unit": "m2",
      "production": null,
      "production_unit": null,
      "market": "Local",
      "observations": null
    },
    {
      "product": "Flores de corte Celosia",
      "variety": null,
      "surface": 50,
      "surface_unit": "m2",
      "production": null,
      "production_unit": null,
      "market": "Local",
      "observations": null
    },
    {
      "product": "Flores fde corte clavelinas",
      "variety": null,
      "surface": 200,
      "surface_unit": "m2",
      "production": null,
      "production_unit": null,
      "market": "Local",
      "observations": null
    },
    {
      "product": "Flores de corte Crisantemo",
      "variety": null,
      "surface": 100,
      "surface_unit": "m2",
      "production": null,
      "production_unit": null,
      "market": "Local",
      "observations": null
    },
    {
      "product": "Flores de corte Gradiolos",
      "variety": null,
      "surface": 100,
      "surface_unit": "m2",
      "production": null,
      "production_unit": null,
      "market": "Local",
      "observations": null
    },
    {
      "product": "Floresde corte Marble",
      "variety": null,
      "surface": 100,
      "surface_unit": "m2",
      "production": null,
      "production_unit": null,
      "market": "Local",
      "observations": null
    },
    {
      "product": "Flores de corte Narcisos",
      "variety": null,
      "surface": 10,
      "surface_unit": "m2",
      "production": null,
      "production_unit": null,
      "market": "Local",
      "observations": null
    },
    {
      "product": "Flores de corte Statice",
      "variety": null,
      "surface": 10,
      "surface_unit": "m2",
      "production": null,
      "production_unit": null,
      "market": "Local",
      "observations": null
    },
    {
      "product": "Lufa",
      "variety": null,
      "surface": 100,
      "surface_unit": "m2",
      "production": null,
      "production_unit": null,
      "market": "Local",
      "observations": null
    },
    {
      "product": "Menta",
      "variety": null,
      "surface": 150,
      "surface_unit": "m2",
      "production": null,
      "production_unit": null,
      "market": "Local",
      "observations": null
    },
    {
      "product": "Kale",
      "variety": null,
      "surface": 200,
      "surface_unit": "m2",
      "production": null,
      "production_unit": null,
      "market": "Local",
      "observations": null
    },
    {
      "product": "Mizuna",
      "variety": null,
      "surface": 60,
      "surface_unit": "m2",
      "production": null,
      "production_unit": null,
      "market": "Local",
      "observations": null
    },
    {
      "product": "Pepino de Invernadero",
      "variety": null,
      "surface": 400,
      "surface_unit": "m2",
      "production": null,
      "production_unit": null,
      "market": "Local",
      "observations": null
    },
    {
      "product": "Perejil",
      "variety": null,
      "surface": 100,
      "surface_unit": "m2",
      "production": null,
      "production_unit": null,
      "market": "Local",
      "observations": null
    },
    {
      "product": "Pimentón Invernadero",
      "variety": null,
      "surface": 100,
      "surface_unit": "m2",
      "production": null,
      "production_unit": null,
      "market": "Local",
      "observations": null
    },
    {
      "product": "Rábanito",
      "variety": "ruby",
      "surface": 240,
      "surface_unit": "m2",
      "production": null,
      "production_unit": null,
      "market": "Local",
      "observations": null
    },
    {
      "product": "Rúcula",
      "variety": "rustica,",
      "surface": 400,
      "surface_unit": "m2",
      "production": null,
      "production_unit": null,
      "market": "Local",
      "observations": null
    },
    {
      "product": "Tatsoi",
      "variety": null,
      "surface": 60,
      "surface_unit": "m2",
      "production": null,
      "production_unit": null,
      "market": "Local",
      "observations": null
    },
    {
      "product": "Tomate Invernadero",
      "variety": null,
      "surface": 650,
      "surface_unit": "m2",
      "production": null,
      "production_unit": null,
      "market": "Local",
      "observations": null
    },
    {
      "product": "Tomate Cherry",
      "variety": null,
      "surface": 100,
      "surface_unit": "m2",
      "production": null,
      "production_unit": null,
      "market": "Local",
      "observations": null
    },
    {
      "product": "Zapallito italiano",
      "variety": "ercules",
      "surface": 200,
      "surface_unit": "m2",
      "production": null,
      "production_unit": null,
      "market": "Local",
      "observations": null
    },
    {
      "product": "Cereza",
      "variety": null,
      "surface": 3500,
      "surface_unit": "m2",
      "production": null,
      "production_unit": null,
      "market": "Local",
      "observations": null
    },
    {
      "product": "Cedrón",
      "variety": null,
      "surface": null,
      "surface_unit": "m2",
      "production": null,
      "production_unit": null,
      "market": "Local",
      "observations": null
    },
    {
      "product": "Ciruela silvestres",
      "variety": null,
      "surface": null,
      "surface_unit": "m2",
      "production": null,
      "production_unit": null,
      "market": "Local",
      "observations": null
    },
    {
      "product": "Ciruela",
      "variety": null,
      "surface": null,
      "surface_unit": "m2",
      "production": null,
      "production_unit": null,
      "market": "Local",
      "observations": null
    },
    {
      "product": "Damasco",
      "variety": null,
      "surface": null,
      "surface_unit": "m2",
      "production": null,
      "production_unit": null,
      "market": "Local",
      "observations": null
    },
    {
      "product": "Durazno",
      "variety": null,
      "surface": null,
      "surface_unit": "m2",
      "production": null,
      "production_unit": null,
      "market": "Local",
      "observations": null
    },
    {
      "product": "Granada",
      "variety": null,
      "surface": null,
      "surface_unit": "m2",
      "production": null,
      "production_unit": null,
      "market": "Local",
      "observations": null
    },
    {
      "product": "Laurel",
      "variety": null,
      "surface": null,
      "surface_unit": "m2",
      "production": null,
      "production_unit": null,
      "market": "Local",
      "observations": null
    },
    {
      "product": "Limón",
      "variety": null,
      "surface": null,
      "surface_unit": "m2",
      "production": null,
      "production_unit": null,
      "market": "Local",
      "observations": null
    },
    {
      "product": "Mandarina",
      "variety": null,
      "surface": null,
      "surface_unit": "m2",
      "production": null,
      "production_unit": null,
      "market": "Local",
      "observations": null
    },
    {
      "product": "Manzana",
      "variety": null,
      "surface": null,
      "surface_unit": "m2",
      "production": null,
      "production_unit": null,
      "market": "Local",
      "observations": null
    },
    {
      "product": "Membrillo",
      "variety": null,
      "surface": null,
      "surface_unit": "m2",
      "production": null,
      "production_unit": null,
      "market": "Local",
      "observations": null
    },
    {
      "product": "Naranja",
      "variety": null,
      "surface": null,
      "surface_unit": "m2",
      "production": null,
      "production_unit": null,
      "market": "Local",
      "observations": null
    },
    {
      "product": "Nogal",
      "variety": null,
      "surface": null,
      "surface_unit": "m2",
      "production": null,
      "production_unit": null,
      "market": "Local",
      "observations": null
    },
    {
      "product": "Olivo",
      "variety": null,
      "surface": null,
      "surface_unit": "m2",
      "production": null,
      "production_unit": null,
      "market": "Local",
      "observations": null
    },
    {
      "product": "Palto",
      "variety": null,
      "surface": null,
      "surface_unit": "m2",
      "production": null,
      "production_unit": null,
      "market": "Local",
      "observations": null
    },
    {
      "product": "Pera",
      "variety": null,
      "surface": null,
      "surface_unit": "m2",
      "production": null,
      "production_unit": null,
      "market": "Local",
      "observations": null
    },
    {
      "product": "Pomelo",
      "variety": null,
      "surface": null,
      "surface_unit": "m2",
      "production": null,
      "production_unit": null,
      "market": "Local",
      "observations": null
    },
    {
      "product": "Borraja flor",
      "variety": null,
      "surface": 50,
      "surface_unit": "m2",
      "production": null,
      "production_unit": null,
      "market": "Local",
      "observations": null
    },
    {
      "product": "Tomillo fresco y/o seco",
      "variety": null,
      "surface": 100,
      "surface_unit": "m2",
      "production": null,
      "production_unit": null,
      "market": "Local",
      "observations": null
    },
    {
      "product": "Acelga",
      "variety": "Crespa ,lisa y colores",
      "surface": 500,
      "surface_unit": "m2",
      "production": null,
      "production_unit": null,
      "market": "Local",
      "observations": null
    },
    {
      "product": "Achicoria",
      "variety": null,
      "surface": 100,
      "surface_unit": "m2",
      "production": null,
      "production_unit": null,
      "market": "Local",
      "observations": null
    },
    {
      "product": "Ají",
      "variety": "cristal, americano, cacho de cabra",
      "surface": 70,
      "surface_unit": "m2",
      "production": null,
      "production_unit": null,
      "market": "Local",
      "observations": null
    },
    {
      "product": "Albahaca",
      "variety": "chilena",
      "surface": 100,
      "surface_unit": "m2",
      "production": null,
      "production_unit": null,
      "market": "Local",
      "observations": null
    },
    {
      "product": "Arvejas",
      "variety": "arverjon",
      "surface": 500,
      "surface_unit": "m2",
      "production": null,
      "production_unit": null,
      "market": "Local",
      "observations": null
    },
    {
      "product": "Apio",
      "variety": null,
      "surface": 900,
      "surface_unit": "m2",
      "production": null,
      "production_unit": null,
      "market": "Local",
      "observations": null
    },
    {
      "product": "Berenjena",
      "variety": null,
      "surface": 300,
      "surface_unit": "m2",
      "production": null,
      "production_unit": null,
      "market": "Local",
      "observations": null
    },
    {
      "product": "Brócoli",
      "variety": null,
      "surface": 1700,
      "surface_unit": "m2",
      "production": null,
      "production_unit": null,
      "market": "Local",
      "observations": null
    },
    {
      "product": "Cebollín blanco",
      "variety": null,
      "surface": 200,
      "surface_unit": "m2",
      "production": null,
      "production_unit": null,
      "market": "Local",
      "observations": null
    },
    {
      "product": "Coliflor",
      "variety": null,
      "surface": 600,
      "surface_unit": "m2",
      "production": null,
      "production_unit": null,
      "market": "Local",
      "observations": null
    },
    {
      "product": "Espinaca",
      "variety": null,
      "surface": 400,
      "surface_unit": "m2",
      "production": null,
      "production_unit": null,
      "market": "Local",
      "observations": null
    },
    {
      "product": "Frambuesas",
      "variety": null,
      "surface": 900,
      "surface_unit": "m2",
      "production": null,
      "production_unit": null,
      "market": "Local",
      "observations": null
    },
    {
      "product": "Garbanzo",
      "variety": null,
      "surface": 600,
      "surface_unit": "m2",
      "production": null,
      "production_unit": null,
      "market": "Local",
      "observations": null
    },
    {
      "product": "Habas",
      "variety": "Agua dulce y luz de Otoño",
      "surface": 200,
      "surface_unit": "m2",
      "production": null,
      "production_unit": null,
      "market": "Local",
      "observations": null
    },
    {
      "product": "Lechuga",
      "variety": "Marinas, costina,francesas, españolas.",
      "surface": 1200,
      "surface_unit": "m2",
      "production": null,
      "production_unit": null,
      "market": "Local",
      "observations": null
    },
    {
      "product": "Kale",
      "variety": "crespo, toscano, russian, lizo",
      "surface": 350,
      "surface_unit": "m2",
      "production": null,
      "production_unit": null,
      "market": "Local",
      "observations": null
    },
    {
      "product": "choclo",
      "variety": "graciela",
      "surface": 800,
      "surface_unit": "m2",
      "production": null,
      "production_unit": null,
      "market": "Local",
      "observations": null
    },
    {
      "product": "Choclo dulce",
      "variety": null,
      "surface": 400,
      "surface_unit": "m2",
      "production": null,
      "production_unit": null,
      "market": "Local",
      "observations": null
    },
    {
      "product": "Maní",
      "variety": "valencia",
      "surface": 560,
      "surface_unit": "m2",
      "production": null,
      "production_unit": null,
      "market": "Local",
      "observations": null
    },
    {
      "product": "Maíz curagua",
      "variety": null,
      "surface": 50,
      "surface_unit": "m2",
      "production": null,
      "production_unit": null,
      "market": "Local",
      "observations": null
    },
    {
      "product": "Poroto mum",
      "variety": "Mun",
      "surface": 700,
      "surface_unit": "m2",
      "production": null,
      "production_unit": null,
      "market": "Local",
      "observations": null
    },
    {
      "product": "Pimenton",
      "variety": null,
      "surface": 70,
      "surface_unit": "m2",
      "production": null,
      "production_unit": null,
      "market": "Local",
      "observations": null
    },
    {
      "product": "Puerro",
      "variety": null,
      "surface": 140,
      "surface_unit": "m2",
      "production": null,
      "production_unit": null,
      "market": "Local",
      "observations": null
    },
    {
      "product": "Rabanito",
      "variety": null,
      "surface": 140,
      "surface_unit": "m2",
      "production": null,
      "production_unit": null,
      "market": "Local",
      "observations": null
    },
    {
      "product": "Repollo crespo",
      "variety": null,
      "surface": 1200,
      "surface_unit": "m2",
      "production": null,
      "production_unit": null,
      "market": "Local",
      "observations": null
    },
    {
      "product": "Repollo liso",
      "variety": "corazon de buey, redondo",
      "surface": 1200,
      "surface_unit": "m2",
      "production": null,
      "production_unit": null,
      "market": "Local",
      "observations": null
    },
    {
      "product": "Repollo morado",
      "variety": null,
      "surface": 800,
      "surface_unit": "m2",
      "production": null,
      "production_unit": null,
      "market": "Local",
      "observations": null
    },
    {
      "product": "Flores calendula",
      "variety": null,
      "surface": 70,
      "surface_unit": "m2",
      "production": null,
      "production_unit": null,
      "market": "Local",
      "observations": null
    },
    {
      "product": "Tomate",
      "variety": null,
      "surface": 1000,
      "surface_unit": "m2",
      "production": null,
      "production_unit": null,
      "market": "Local",
      "observations": null
    },
    {
      "product": "Tomate Salsero",
      "variety": null,
      "surface": 500,
      "surface_unit": "m2",
      "production": null,
      "production_unit": null,
      "market": "Local",
      "observations": null
    },
    {
      "product": "Zapallo baternut",
      "variety": null,
      "surface": 1000,
      "surface_unit": "m2",
      "production": null,
      "production_unit": null,
      "market": "Local",
      "observations": null
    },
    {
      "product": "Zapallo naranja",
      "variety": null,
      "surface": 500,
      "surface_unit": "m2",
      "production": null,
      "production_unit": null,
      "market": "Local",
      "observations": null
    },
    {
      "product": "Zapallo camote",
      "variety": null,
      "surface": 1500,
      "surface_unit": "m2",
      "production": null,
      "production_unit": null,
      "market": "Local",
      "observations": null
    },
    {
      "product": "Limón",
      "variety": null,
      "surface": null,
      "surface_unit": "m2",
      "production": null,
      "production_unit": null,
      "market": "Local",
      "observations": null
    },
    {
      "product": "Parras",
      "variety": "Pais",
      "surface": null,
      "surface_unit": "m2",
      "production": null,
      "production_unit": null,
      "market": "Local",
      "observations": null
    },
    {
      "product": "Paltos",
      "variety": "palta chilena",
      "surface": null,
      "surface_unit": "m2",
      "production": null,
      "production_unit": null,
      "market": "Local",
      "observations": null
    },
    {
      "product": "PAlfalfa",
      "variety": null,
      "surface": 2500,
      "surface_unit": "m2",
      "production": null,
      "production_unit": null,
      "market": "Local",
      "observations": null
    },
    {
      "product": "Acelga",
      "variety": "penca blanca",
      "surface": 1200,
      "surface_unit": "m2",
      "production": null,
      "production_unit": null,
      "market": "Local",
      "observations": null
    },
    {
      "product": "Betarraga",
      "variety": "chata egipto",
      "surface": 500,
      "surface_unit": "m2",
      "production": null,
      "production_unit": null,
      "market": "Local",
      "observations": null
    },
    {
      "product": "Arveja",
      "variety": null,
      "surface": 240,
      "surface_unit": "m2",
      "production": null,
      "production_unit": null,
      "market": "Local",
      "observations": null
    },
    {
      "product": "Cilantro",
      "variety": null,
      "surface": 150,
      "surface_unit": "m2",
      "production": null,
      "production_unit": null,
      "market": "Local",
      "observations": null
    },
    {
      "product": "Kale",
      "variety": "russian",
      "surface": 300,
      "surface_unit": "m2",
      "production": null,
      "production_unit": null,
      "market": "Local",
      "observations": null
    },
    {
      "product": "Lechuga",
      "variety": null,
      "surface": 1000,
      "surface_unit": "m2",
      "production": null,
      "production_unit": null,
      "market": "Local",
      "observations": null
    },
    {
      "product": "Haba",
      "variety": "Agua Dulce",
      "surface": 5000,
      "surface_unit": "m2",
      "production": null,
      "production_unit": null,
      "market": "Local",
      "observations": null
    },
    {
      "product": "Papa",
      "variety": null,
      "surface": 1300,
      "surface_unit": "m2",
      "production": null,
      "production_unit": null,
      "market": "Local",
      "observations": null
    },
    {
      "product": "Pepino ensalada",
      "variety": "Marketmore",
      "surface": 600,
      "surface_unit": "m2",
      "production": null,
      "production_unit": null,
      "market": "Local",
      "observations": null
    },
    {
      "product": "Zanahoria",
      "variety": null,
      "surface": 700,
      "surface_unit": "m2",
      "production": null,
      "production_unit": null,
      "market": "Local",
      "observations": null
    },
    {
      "product": "Choclos",
      "variety": null,
      "surface": 2000,
      "surface_unit": "m2",
      "production": null,
      "production_unit": null,
      "market": "Local",
      "observations": null
    },
    {
      "product": "Zapallito Italiano",
      "variety": null,
      "surface": 1000,
      "surface_unit": "m2",
      "production": null,
      "production_unit": null,
      "market": "Local",
      "observations": null
    }
  ]
}
