{
  "id": 2,
  "country": "Chile",
  "city": "La Cruz",
  "name": "CHAKRA VERDE SER",
  "contact": "Marcela Garcia",
  "whatsapp": "56985374849",
  "email": "marcelagarciato@gmail.com",
  "organic_certification": "CERTIFICADO",
  "bd_certification": "DEMETER - BD",
  "parcels": [
    {
      "product": "Palto",
      "variety": null,
      "surface": 1,
      "surface_unit": null,
      "production": null,
      "production_unit": null,
      "market": "Local",
      "observations": null
    },
    {
      "product": "Palto",
      "variety": null,
      "surface": 1.7,
      "surface_unit": null,
      "production": null,
      "production_unit": null,
      "market": "Local",
      "observations": null
    },
    {
      "product": "Palto",
      "variety": null,
      "surface": 1.2,
      "surface_unit": null,
      "production": null,
      "production_unit": null,
      "market": "Local",
      "observations": null
    },
    {
      "product": "Hortalizas",
      "variety": null,
      "surface": 0.1,
      "surface_unit": null,
      "production": null,
      "production_unit": null,
      "market": "Local",
      "observations": null
    },
    {
      "product": "Paltos (primavera 21)",
      "variety": null,
      "surface": 0.1,
      "surface_unit": null,
      "production": null,
      "production_unit": null,
      "market": "Local",
      "observations": null
    },
    {
      "product": "Pastura Mixta (primavera 21)",
      "variety": null,
      "surface": 0.1,
      "surface_unit": null,
      "production": null,
      "production_unit": null,
      "market": "Local",
      "observations": null
    },
    {
      "product": "Palto",
      "variety": null,
      "surface": 1.45,
      "surface_unit": null,
      "production": null,
      "production_unit": null,
      "market": "Local",
      "observations": null
    },
    {
      "product": "Hortalizas",
      "variety": null,
      "surface": 0.05,
      "surface_unit": null,
      "production": null,
      "production_unit": null,
      "market": "Local",
      "observations": null
    },
    {
      "product": "Palto",
      "variety": null,
      "surface": 1,
      "surface_unit": null,
      "production": null,
      "production_unit": null,
      "market": "Local",
      "observations": null
    },
    {
      "product": "Palto",
      "variety": null,
      "surface": 0.9,
      "surface_unit": null,
      "production": null,
      "production_unit": null,
      "market": "Local",
      "observations": null
    },
    {
      "product": "Palto Hass",
      "variety": null,
      "surface": 0.4,
      "surface_unit": null,
      "production": null,
      "production_unit": null,
      "market": "Local",
      "observations": null
    },
    {
      "product": "Paltos y Frutales varios ( duraznos, manzanos, perales, nogales, almendros, damascos, ciruelas, naranjos, feijoa boysenberry, frambuesa)",
      "variety": null,
      "surface": 0.4,
      "surface_unit": null,
      "production": null,
      "production_unit": null,
      "market": "Local",
      "observations": null
    }
  ]
}
